{
	"pages": [ //pages数组中第一项表示应用启动页，参考：https://uniapp.dcloud.io/collocation/pages
		{
			"path": "pages/tabBar/home/home",
			"style": {
				"navigationBarTitleText": "首页",
				"app-plus": {
					"titleNView": false
				}
			}
		},
		{
			"path":"pages/tabBar/home/article",
			"style": {
				"navigationBarTitleText":"今天头条"
			}
		},
	    {
            "path" : "pages/tabBar/video/video",
            "style" : {
				"navigationBarTitleText":"视频"
			}
        },
		{
		    "path" : "pages/tabBar/video/videoDetail",
		    "style" : {
				"navigationBarTitleText":"视频详情"
			}
		},
        {
            "path" : "pages/tabBar/publish/publish",
            "style" : {
				"navigationBarTitleText":"",
				"app-plus": {
					"titleNView": {
						"buttons": [
							{"text":"取消", "fontSize":"18px", "float":"left"},
							{"text": "发布", "fontSize":"18px", "float":"right"}
						]
					}
				}
			}
        }
    ],
	"globalStyle": {
		"navigationBarTextStyle": "white",
		"navigationBarTitleText": "每日头条",
		"navigationBarBackgroundColor": "#d43d3d",
		"backgroundColor": "#FFFFFF"
	},
	"tabBar": {
		"color":"#8F8F94",
		"selectedColor":"#f33e54",
		"backgroundColor":"#F8F8F8",
		"list": [
			{
				"pagePath":"pages/tabBar/home/home",
				"iconPath":"static/img/tabbar/home.png",
				"selectedIconPath":"static/img/tabbar/homeactive.png",
				"text":"首页"
			},
			{
				"pagePath":"pages/tabBar/publish/publish",
				"iconPath":"static/img/tabbar/add.png",
				"selectedIconPath":"static/img/tabbar/addactive.png",
				"text":"发布"
			},
			{
				"pagePath":"pages/tabBar/video/video",
				"iconPath":"static/img/tabbar/guanzhu.png",
				"selectedIconPath":"static/img/tabbar/guanzhuactive.png",
				"text":"视频"
			}
		]
	}
	
}
